scrapy_sqs/__init__.py
scrapy_sqs/connection.py
scrapy_sqs/spiders.py
scrapy_sqs-0.0.3.dist-info/METADATA
scrapy_sqs-0.0.3.dist-info/WHEEL
scrapy_sqs-0.0.3.dist-info/top_level.txt
scrapy_sqs-0.0.3.dist-info/RECORD
